influxdb_async/__init__.py
influxdb_async/async_api.py
influxdb_async-1.0.1.dist-info/METADATA
influxdb_async-1.0.1.dist-info/WHEEL
influxdb_async-1.0.1.dist-info/top_level.txt
influxdb_async-1.0.1.dist-info/RECORD
