Metadata-Version: 2.1
Name: influxdb-async
Version: 1.0.1
Summary: async multi fields to influxdb
Home-page: https://github.com/yinhuanyi/zabbix-feishu-alert
Author: Robby
Author-email: yinhuanyicn@gmail.com
License: MIT
Platform: UNKNOWN
Requires-Dist: influxdb
